{
  "catalog": {
    "uuid": "e75ab3c9-60ef-4124-bae5-b685fc38fe5c",
    "metadata": {
      "title": "ISO/IEC 42001:2023 AI Management System - Annex A Controls",
      "version": "2023",
      "oscal-version": "1.1.2",
      "last-modified": "2026-03-19T20:45:25Z",
      "links": [
        {
          "rel": "source",
          "href": "https://www.iso.org/standard/81230.html"
        }
      ],
      "props": [
        {
          "name": "framework-key",
          "value": "iso_42001"
        }
      ]
    },
    "groups": [
      {
        "id": "a10",
        "title": "Third-Party and Customer Relationships",
        "controls": [
          {
            "id": "A.10.2",
            "title": "Control A.10.2",
            "props": [
              {
                "name": "label",
                "value": "A.10.2"
              },
              {
                "name": "sort-id",
                "value": "a.10.2"
              },
              {
                "name": "monitoring-frequency",
                "value": "monthly"
              }
            ],
            "parts": [
              {
                "id": "a-10-2_smt",
                "name": "statement",
                "prose": "Requirements for A.10.2."
              }
            ]
          },
          {
            "id": "A.10.3",
            "title": "Control A.10.3",
            "props": [
              {
                "name": "label",
                "value": "A.10.3"
              },
              {
                "name": "sort-id",
                "value": "a.10.3"
              },
              {
                "name": "monitoring-frequency",
                "value": "monthly"
              }
            ],
            "parts": [
              {
                "id": "a-10-3_smt",
                "name": "statement",
                "prose": "Requirements for A.10.3."
              }
            ]
          }
        ]
      },
      {
        "id": "a2",
        "title": "AI Policies",
        "controls": [
          {
            "id": "A.2.2",
            "title": "Control A.2.2",
            "props": [
              {
                "name": "label",
                "value": "A.2.2"
              },
              {
                "name": "sort-id",
                "value": "a.2.2"
              },
              {
                "name": "monitoring-frequency",
                "value": "monthly"
              }
            ],
            "parts": [
              {
                "id": "a-2-2_smt",
                "name": "statement",
                "prose": "Requirements for A.2.2."
              }
            ]
          },
          {
            "id": "A.2.3",
            "title": "Control A.2.3",
            "props": [
              {
                "name": "label",
                "value": "A.2.3"
              },
              {
                "name": "sort-id",
                "value": "a.2.3"
              },
              {
                "name": "monitoring-frequency",
                "value": "monthly"
              }
            ],
            "parts": [
              {
                "id": "a-2-3_smt",
                "name": "statement",
                "prose": "Requirements for A.2.3."
              }
            ]
          },
          {
            "id": "A.2.4",
            "title": "Control A.2.4",
            "props": [
              {
                "name": "label",
                "value": "A.2.4"
              },
              {
                "name": "sort-id",
                "value": "a.2.4"
              },
              {
                "name": "monitoring-frequency",
                "value": "monthly"
              }
            ],
            "parts": [
              {
                "id": "a-2-4_smt",
                "name": "statement",
                "prose": "Requirements for A.2.4."
              }
            ]
          }
        ]
      },
      {
        "id": "a3",
        "title": "Organization of AI",
        "controls": [
          {
            "id": "A.3.2",
            "title": "Control A.3.2",
            "props": [
              {
                "name": "label",
                "value": "A.3.2"
              },
              {
                "name": "sort-id",
                "value": "a.3.2"
              },
              {
                "name": "monitoring-frequency",
                "value": "monthly"
              }
            ],
            "parts": [
              {
                "id": "a-3-2_smt",
                "name": "statement",
                "prose": "Requirements for A.3.2."
              }
            ]
          },
          {
            "id": "A.3.3",
            "title": "Control A.3.3",
            "props": [
              {
                "name": "label",
                "value": "A.3.3"
              },
              {
                "name": "sort-id",
                "value": "a.3.3"
              },
              {
                "name": "monitoring-frequency",
                "value": "monthly"
              }
            ],
            "parts": [
              {
                "id": "a-3-3_smt",
                "name": "statement",
                "prose": "Requirements for A.3.3."
              }
            ]
          }
        ]
      },
      {
        "id": "a4",
        "title": "Support for AI",
        "controls": [
          {
            "id": "A.4.2",
            "title": "Control A.4.2",
            "props": [
              {
                "name": "label",
                "value": "A.4.2"
              },
              {
                "name": "sort-id",
                "value": "a.4.2"
              },
              {
                "name": "monitoring-frequency",
                "value": "monthly"
              }
            ],
            "parts": [
              {
                "id": "a-4-2_smt",
                "name": "statement",
                "prose": "Requirements for A.4.2."
              }
            ]
          },
          {
            "id": "A.4.3",
            "title": "Control A.4.3",
            "props": [
              {
                "name": "label",
                "value": "A.4.3"
              },
              {
                "name": "sort-id",
                "value": "a.4.3"
              },
              {
                "name": "monitoring-frequency",
                "value": "monthly"
              }
            ],
            "parts": [
              {
                "id": "a-4-3_smt",
                "name": "statement",
                "prose": "Requirements for A.4.3."
              }
            ]
          },
          {
            "id": "A.4.4",
            "title": "Control A.4.4",
            "props": [
              {
                "name": "label",
                "value": "A.4.4"
              },
              {
                "name": "sort-id",
                "value": "a.4.4"
              },
              {
                "name": "monitoring-frequency",
                "value": "monthly"
              }
            ],
            "parts": [
              {
                "id": "a-4-4_smt",
                "name": "statement",
                "prose": "Requirements for A.4.4."
              }
            ]
          },
          {
            "id": "A.4.5",
            "title": "Control A.4.5",
            "props": [
              {
                "name": "label",
                "value": "A.4.5"
              },
              {
                "name": "sort-id",
                "value": "a.4.5"
              },
              {
                "name": "monitoring-frequency",
                "value": "monthly"
              }
            ],
            "parts": [
              {
                "id": "a-4-5_smt",
                "name": "statement",
                "prose": "Requirements for A.4.5."
              }
            ]
          },
          {
            "id": "A.4.6",
            "title": "Control A.4.6",
            "props": [
              {
                "name": "label",
                "value": "A.4.6"
              },
              {
                "name": "sort-id",
                "value": "a.4.6"
              },
              {
                "name": "monitoring-frequency",
                "value": "monthly"
              }
            ],
            "parts": [
              {
                "id": "a-4-6_smt",
                "name": "statement",
                "prose": "Requirements for A.4.6."
              }
            ]
          }
        ]
      },
      {
        "id": "a5",
        "title": "AI Impact Assessment",
        "controls": [
          {
            "id": "A.5.2",
            "title": "Control A.5.2",
            "props": [
              {
                "name": "label",
                "value": "A.5.2"
              },
              {
                "name": "sort-id",
                "value": "a.5.2"
              },
              {
                "name": "monitoring-frequency",
                "value": "quarterly"
              }
            ],
            "parts": [
              {
                "id": "a-5-2_smt",
                "name": "statement",
                "prose": "Requirements for A.5.2."
              }
            ]
          },
          {
            "id": "A.5.3",
            "title": "Control A.5.3",
            "props": [
              {
                "name": "label",
                "value": "A.5.3"
              },
              {
                "name": "sort-id",
                "value": "a.5.3"
              },
              {
                "name": "monitoring-frequency",
                "value": "quarterly"
              }
            ],
            "parts": [
              {
                "id": "a-5-3_smt",
                "name": "statement",
                "prose": "Requirements for A.5.3."
              }
            ]
          },
          {
            "id": "A.5.4",
            "title": "Control A.5.4",
            "props": [
              {
                "name": "label",
                "value": "A.5.4"
              },
              {
                "name": "sort-id",
                "value": "a.5.4"
              },
              {
                "name": "monitoring-frequency",
                "value": "quarterly"
              }
            ],
            "parts": [
              {
                "id": "a-5-4_smt",
                "name": "statement",
                "prose": "Requirements for A.5.4."
              }
            ]
          }
        ]
      },
      {
        "id": "a6",
        "title": "AI System Lifecycle",
        "controls": [
          {
            "id": "A.6.1.2",
            "title": "Control A.6.1.2",
            "props": [
              {
                "name": "label",
                "value": "A.6.1.2"
              },
              {
                "name": "sort-id",
                "value": "a.6.1.2"
              },
              {
                "name": "monitoring-frequency",
                "value": "monthly"
              }
            ],
            "parts": [
              {
                "id": "a-6-1-2_smt",
                "name": "statement",
                "prose": "Requirements for A.6.1.2."
              }
            ]
          },
          {
            "id": "A.6.1.3",
            "title": "Control A.6.1.3",
            "props": [
              {
                "name": "label",
                "value": "A.6.1.3"
              },
              {
                "name": "sort-id",
                "value": "a.6.1.3"
              },
              {
                "name": "monitoring-frequency",
                "value": "monthly"
              }
            ],
            "parts": [
              {
                "id": "a-6-1-3_smt",
                "name": "statement",
                "prose": "Requirements for A.6.1.3."
              }
            ]
          },
          {
            "id": "A.6.2.10",
            "title": "Control A.6.2.10",
            "props": [
              {
                "name": "label",
                "value": "A.6.2.10"
              },
              {
                "name": "sort-id",
                "value": "a.6.2.10"
              },
              {
                "name": "monitoring-frequency",
                "value": "monthly"
              }
            ],
            "parts": [
              {
                "id": "a-6-2-10_smt",
                "name": "statement",
                "prose": "Requirements for A.6.2.10."
              }
            ]
          },
          {
            "id": "A.6.2.11",
            "title": "Control A.6.2.11",
            "props": [
              {
                "name": "label",
                "value": "A.6.2.11"
              },
              {
                "name": "sort-id",
                "value": "a.6.2.11"
              },
              {
                "name": "monitoring-frequency",
                "value": "monthly"
              }
            ],
            "parts": [
              {
                "id": "a-6-2-11_smt",
                "name": "statement",
                "prose": "Requirements for A.6.2.11."
              }
            ]
          },
          {
            "id": "A.6.2.12",
            "title": "Control A.6.2.12",
            "props": [
              {
                "name": "label",
                "value": "A.6.2.12"
              },
              {
                "name": "sort-id",
                "value": "a.6.2.12"
              },
              {
                "name": "monitoring-frequency",
                "value": "monthly"
              }
            ],
            "parts": [
              {
                "id": "a-6-2-12_smt",
                "name": "statement",
                "prose": "Requirements for A.6.2.12."
              }
            ]
          },
          {
            "id": "A.6.2.13",
            "title": "Control A.6.2.13",
            "props": [
              {
                "name": "label",
                "value": "A.6.2.13"
              },
              {
                "name": "sort-id",
                "value": "a.6.2.13"
              },
              {
                "name": "monitoring-frequency",
                "value": "monthly"
              }
            ],
            "parts": [
              {
                "id": "a-6-2-13_smt",
                "name": "statement",
                "prose": "Requirements for A.6.2.13."
              }
            ]
          },
          {
            "id": "A.6.2.2",
            "title": "Control A.6.2.2",
            "props": [
              {
                "name": "label",
                "value": "A.6.2.2"
              },
              {
                "name": "sort-id",
                "value": "a.6.2.2"
              },
              {
                "name": "monitoring-frequency",
                "value": "monthly"
              }
            ],
            "parts": [
              {
                "id": "a-6-2-2_smt",
                "name": "statement",
                "prose": "Requirements for A.6.2.2."
              }
            ]
          },
          {
            "id": "A.6.2.3",
            "title": "Control A.6.2.3",
            "props": [
              {
                "name": "label",
                "value": "A.6.2.3"
              },
              {
                "name": "sort-id",
                "value": "a.6.2.3"
              },
              {
                "name": "monitoring-frequency",
                "value": "monthly"
              }
            ],
            "parts": [
              {
                "id": "a-6-2-3_smt",
                "name": "statement",
                "prose": "Requirements for A.6.2.3."
              }
            ]
          },
          {
            "id": "A.6.2.4",
            "title": "Control A.6.2.4",
            "props": [
              {
                "name": "label",
                "value": "A.6.2.4"
              },
              {
                "name": "sort-id",
                "value": "a.6.2.4"
              },
              {
                "name": "monitoring-frequency",
                "value": "monthly"
              }
            ],
            "parts": [
              {
                "id": "a-6-2-4_smt",
                "name": "statement",
                "prose": "Requirements for A.6.2.4."
              }
            ]
          },
          {
            "id": "A.6.2.5",
            "title": "Control A.6.2.5",
            "props": [
              {
                "name": "label",
                "value": "A.6.2.5"
              },
              {
                "name": "sort-id",
                "value": "a.6.2.5"
              },
              {
                "name": "monitoring-frequency",
                "value": "monthly"
              }
            ],
            "parts": [
              {
                "id": "a-6-2-5_smt",
                "name": "statement",
                "prose": "Requirements for A.6.2.5."
              }
            ]
          },
          {
            "id": "A.6.2.6",
            "title": "Control A.6.2.6",
            "props": [
              {
                "name": "label",
                "value": "A.6.2.6"
              },
              {
                "name": "sort-id",
                "value": "a.6.2.6"
              },
              {
                "name": "monitoring-frequency",
                "value": "monthly"
              }
            ],
            "parts": [
              {
                "id": "a-6-2-6_smt",
                "name": "statement",
                "prose": "Requirements for A.6.2.6."
              }
            ]
          },
          {
            "id": "A.6.2.7",
            "title": "Control A.6.2.7",
            "props": [
              {
                "name": "label",
                "value": "A.6.2.7"
              },
              {
                "name": "sort-id",
                "value": "a.6.2.7"
              },
              {
                "name": "monitoring-frequency",
                "value": "monthly"
              }
            ],
            "parts": [
              {
                "id": "a-6-2-7_smt",
                "name": "statement",
                "prose": "Requirements for A.6.2.7."
              }
            ]
          },
          {
            "id": "A.6.2.8",
            "title": "Control A.6.2.8",
            "props": [
              {
                "name": "label",
                "value": "A.6.2.8"
              },
              {
                "name": "sort-id",
                "value": "a.6.2.8"
              },
              {
                "name": "monitoring-frequency",
                "value": "monthly"
              }
            ],
            "parts": [
              {
                "id": "a-6-2-8_smt",
                "name": "statement",
                "prose": "Requirements for A.6.2.8."
              }
            ]
          },
          {
            "id": "A.6.2.9",
            "title": "Control A.6.2.9",
            "props": [
              {
                "name": "label",
                "value": "A.6.2.9"
              },
              {
                "name": "sort-id",
                "value": "a.6.2.9"
              },
              {
                "name": "monitoring-frequency",
                "value": "monthly"
              }
            ],
            "parts": [
              {
                "id": "a-6-2-9_smt",
                "name": "statement",
                "prose": "Requirements for A.6.2.9."
              }
            ]
          }
        ]
      },
      {
        "id": "a7",
        "title": "Data for AI Systems",
        "controls": [
          {
            "id": "A.7.2",
            "title": "Control A.7.2",
            "props": [
              {
                "name": "label",
                "value": "A.7.2"
              },
              {
                "name": "sort-id",
                "value": "a.7.2"
              },
              {
                "name": "monitoring-frequency",
                "value": "monthly"
              }
            ],
            "parts": [
              {
                "id": "a-7-2_smt",
                "name": "statement",
                "prose": "Requirements for A.7.2."
              }
            ]
          },
          {
            "id": "A.7.3",
            "title": "Control A.7.3",
            "props": [
              {
                "name": "label",
                "value": "A.7.3"
              },
              {
                "name": "sort-id",
                "value": "a.7.3"
              },
              {
                "name": "monitoring-frequency",
                "value": "monthly"
              }
            ],
            "parts": [
              {
                "id": "a-7-3_smt",
                "name": "statement",
                "prose": "Requirements for A.7.3."
              }
            ]
          },
          {
            "id": "A.7.4",
            "title": "Control A.7.4",
            "props": [
              {
                "name": "label",
                "value": "A.7.4"
              },
              {
                "name": "sort-id",
                "value": "a.7.4"
              },
              {
                "name": "monitoring-frequency",
                "value": "monthly"
              }
            ],
            "parts": [
              {
                "id": "a-7-4_smt",
                "name": "statement",
                "prose": "Requirements for A.7.4."
              }
            ]
          },
          {
            "id": "A.7.5",
            "title": "Control A.7.5",
            "props": [
              {
                "name": "label",
                "value": "A.7.5"
              },
              {
                "name": "sort-id",
                "value": "a.7.5"
              },
              {
                "name": "monitoring-frequency",
                "value": "monthly"
              }
            ],
            "parts": [
              {
                "id": "a-7-5_smt",
                "name": "statement",
                "prose": "Requirements for A.7.5."
              }
            ]
          }
        ]
      },
      {
        "id": "a8",
        "title": "Transparency and Provision of Information",
        "controls": [
          {
            "id": "A.8.2",
            "title": "Control A.8.2",
            "props": [
              {
                "name": "label",
                "value": "A.8.2"
              },
              {
                "name": "sort-id",
                "value": "a.8.2"
              },
              {
                "name": "monitoring-frequency",
                "value": "monthly"
              }
            ],
            "parts": [
              {
                "id": "a-8-2_smt",
                "name": "statement",
                "prose": "Requirements for A.8.2."
              }
            ]
          },
          {
            "id": "A.8.3",
            "title": "Control A.8.3",
            "props": [
              {
                "name": "label",
                "value": "A.8.3"
              },
              {
                "name": "sort-id",
                "value": "a.8.3"
              },
              {
                "name": "monitoring-frequency",
                "value": "monthly"
              }
            ],
            "parts": [
              {
                "id": "a-8-3_smt",
                "name": "statement",
                "prose": "Requirements for A.8.3."
              }
            ]
          },
          {
            "id": "A.8.4",
            "title": "Control A.8.4",
            "props": [
              {
                "name": "label",
                "value": "A.8.4"
              },
              {
                "name": "sort-id",
                "value": "a.8.4"
              },
              {
                "name": "monitoring-frequency",
                "value": "monthly"
              }
            ],
            "parts": [
              {
                "id": "a-8-4_smt",
                "name": "statement",
                "prose": "Requirements for A.8.4."
              }
            ]
          }
        ]
      },
      {
        "id": "a9",
        "title": "Use of AI Systems",
        "controls": [
          {
            "id": "A.9.2",
            "title": "Control A.9.2",
            "props": [
              {
                "name": "label",
                "value": "A.9.2"
              },
              {
                "name": "sort-id",
                "value": "a.9.2"
              },
              {
                "name": "monitoring-frequency",
                "value": "weekly"
              }
            ],
            "parts": [
              {
                "id": "a-9-2_smt",
                "name": "statement",
                "prose": "Requirements for A.9.2."
              }
            ]
          },
          {
            "id": "A.9.3",
            "title": "Control A.9.3",
            "props": [
              {
                "name": "label",
                "value": "A.9.3"
              },
              {
                "name": "sort-id",
                "value": "a.9.3"
              },
              {
                "name": "monitoring-frequency",
                "value": "weekly"
              }
            ],
            "parts": [
              {
                "id": "a-9-3_smt",
                "name": "statement",
                "prose": "Requirements for A.9.3."
              }
            ]
          },
          {
            "id": "A.9.4",
            "title": "Control A.9.4",
            "props": [
              {
                "name": "label",
                "value": "A.9.4"
              },
              {
                "name": "sort-id",
                "value": "a.9.4"
              },
              {
                "name": "monitoring-frequency",
                "value": "weekly"
              }
            ],
            "parts": [
              {
                "id": "a-9-4_smt",
                "name": "statement",
                "prose": "Requirements for A.9.4."
              }
            ]
          }
        ]
      }
    ]
  }
}
